tmobile_call_log/__init__.py
tmobile_call_log/tmobile_call_log.py
tmobile_call_log-0.1.0.dist-info/LICENSE
tmobile_call_log-0.1.0.dist-info/WHEEL
tmobile_call_log-0.1.0.dist-info/METADATA
tmobile_call_log-0.1.0.dist-info/RECORD
