Metadata-Version: 2.1
Name: tmobile-call-log
Version: 0.1.0
Summary: Creates plots from T-Mobile personal call logs.
Home-page: UNKNOWN
License: MIT
Author: Manny Ochoa
Author-email: dev@manuelochoa.com
Requires-Python: >=3.6,<4.0
Classifier: License :: OSI Approved :: MIT License
Classifier: Programming Language :: Python :: 3
Classifier: Programming Language :: Python :: 3.6
Classifier: Programming Language :: Python :: 3.7
Requires-Dist: matplotlib (>=3.0,<4.0)
Requires-Dist: numpy (>=1.15,<2.0)
Requires-Dist: pandas (>=0.23.4,<0.24.0)
